{
  "generated_at": "2026-07-05T11:27:10.133400+00:00",
  "source": "https://api.energidataservice.dk/dataset/ElectricityProdex5MinRealtime",
  "areas": {
    "DK1": {
      "price_area": "DK1",
      "timestamp_utc": "2026-07-05T11:20:00",
      "onshore_mw": 2021.439941,
      "offshore_mw": 911.359985,
      "total_mw": 2932.799926
    },
    "DK2": {
      "price_area": "DK2",
      "timestamp_utc": "2026-07-05T11:20:00",
      "onshore_mw": 325.429993,
      "offshore_mw": 218.850006,
      "total_mw": 544.2799990000001
    }
  },
  "totals": {
    "onshore_mw": 2346.8699340000003,
    "offshore_mw": 1130.2099910000002,
    "total_mw": 3477.0799250000005
  },
  "latest_timestamp_utc": "2026-07-05T11:20:00"
}