{
  "generated_at": "2026-01-22T04:45:35.110837+00:00",
  "source": "https://api.energidataservice.dk/dataset/ElectricityProdex5MinRealtime",
  "areas": {
    "DK1": {
      "price_area": "DK1",
      "timestamp_utc": "2026-01-22T04:40:00",
      "onshore_mw": 2437.169922,
      "offshore_mw": 1480.040039,
      "total_mw": 3917.209961
    },
    "DK2": {
      "price_area": "DK2",
      "timestamp_utc": "2026-01-22T04:40:00",
      "onshore_mw": 389.950012,
      "offshore_mw": 906.809998,
      "total_mw": 1296.76001
    }
  },
  "totals": {
    "onshore_mw": 2827.1199340000003,
    "offshore_mw": 2386.850037,
    "total_mw": 5213.969971
  },
  "latest_timestamp_utc": "2026-01-22T04:40:00"
}