{
  "generated_at": "2026-06-07T08:19:48.500724+00:00",
  "source": "https://api.energidataservice.dk/dataset/ElectricityProdex5MinRealtime",
  "areas": {
    "DK1": {
      "price_area": "DK1",
      "timestamp_utc": "2026-06-07T08:15:00",
      "onshore_mw": 228.240005,
      "offshore_mw": 3.69,
      "total_mw": 231.930005
    },
    "DK2": {
      "price_area": "DK2",
      "timestamp_utc": "2026-06-07T08:15:00",
      "onshore_mw": 46.43,
      "offshore_mw": 1.08,
      "total_mw": 47.51
    }
  },
  "totals": {
    "onshore_mw": 274.670005,
    "offshore_mw": 4.77,
    "total_mw": 279.440005
  },
  "latest_timestamp_utc": "2026-06-07T08:15:00"
}