{
  "generated_at": "2025-12-16T19:15:48.050132+00:00",
  "source": "https://api.energidataservice.dk/dataset/ElectricityProdex5MinRealtime",
  "areas": {
    "DK1": {
      "price_area": "DK1",
      "timestamp_utc": "2025-12-16T19:10:00",
      "onshore_mw": 1037.800049,
      "offshore_mw": 591.51001,
      "total_mw": 1629.310059
    },
    "DK2": {
      "price_area": "DK2",
      "timestamp_utc": "2025-12-16T19:10:00",
      "onshore_mw": 167.070007,
      "offshore_mw": 632.609985,
      "total_mw": 799.6799920000001
    }
  },
  "totals": {
    "onshore_mw": 1204.870056,
    "offshore_mw": 1224.119995,
    "total_mw": 2428.9900509999998
  },
  "latest_timestamp_utc": "2025-12-16T19:10:00"
}