{
  "generated_at": "2025-12-22T03:27:45.226234+00:00",
  "source": "https://api.energidataservice.dk/dataset/ElectricityProdex5MinRealtime",
  "areas": {
    "DK1": {
      "price_area": "DK1",
      "timestamp_utc": "2025-12-22T03:25:00",
      "onshore_mw": 1246.030029,
      "offshore_mw": 1104.670044,
      "total_mw": 2350.700073
    },
    "DK2": {
      "price_area": "DK2",
      "timestamp_utc": "2025-12-22T03:25:00",
      "onshore_mw": 264.359985,
      "offshore_mw": 649.52002,
      "total_mw": 913.880005
    }
  },
  "totals": {
    "onshore_mw": 1510.390014,
    "offshore_mw": 1754.190064,
    "total_mw": 3264.580078
  },
  "latest_timestamp_utc": "2025-12-22T03:25:00"
}