{
  "generated_at": "2025-11-27T18:20:43.465629+00:00",
  "source": "https://api.energidataservice.dk/dataset/ElectricityProdex5MinRealtime",
  "areas": {
    "DK1": {
      "price_area": "DK1",
      "timestamp_utc": "2025-11-27T18:15:00",
      "onshore_mw": 2657.550049,
      "offshore_mw": 1477.219971,
      "total_mw": 4134.77002
    },
    "DK2": {
      "price_area": "DK2",
      "timestamp_utc": "2025-11-27T18:15:00",
      "onshore_mw": 462.100006,
      "offshore_mw": 972.679993,
      "total_mw": 1434.7799989999999
    }
  },
  "totals": {
    "onshore_mw": 3119.650055,
    "offshore_mw": 2449.899964,
    "total_mw": 5569.550019
  },
  "latest_timestamp_utc": "2025-11-27T18:15:00"
}