{
  "generated_at": "2025-11-24T20:17:00.033507+00:00",
  "source": "https://api.energidataservice.dk/dataset/ElectricityProdex5MinRealtime",
  "areas": {
    "DK1": {
      "price_area": "DK1",
      "timestamp_utc": "2025-11-24T20:10:00",
      "onshore_mw": 1292.400024,
      "offshore_mw": 1306.180054,
      "total_mw": 2598.580078
    },
    "DK2": {
      "price_area": "DK2",
      "timestamp_utc": "2025-11-24T20:10:00",
      "onshore_mw": 142.820007,
      "offshore_mw": 349.440002,
      "total_mw": 492.26000899999997
    }
  },
  "totals": {
    "onshore_mw": 1435.220031,
    "offshore_mw": 1655.620056,
    "total_mw": 3090.840087
  },
  "latest_timestamp_utc": "2025-11-24T20:10:00"
}