{
  "generated_at": "2026-01-20T11:20:35.313245+00:00",
  "source": "https://api.energidataservice.dk/dataset/ElectricityProdex5MinRealtime",
  "areas": {
    "DK1": {
      "price_area": "DK1",
      "timestamp_utc": "2026-01-20T11:15:00",
      "onshore_mw": 149.589996,
      "offshore_mw": 167.899994,
      "total_mw": 317.48999000000003
    },
    "DK2": {
      "price_area": "DK2",
      "timestamp_utc": "2026-01-20T11:15:00",
      "onshore_mw": 9.04,
      "offshore_mw": 3.83,
      "total_mw": 12.87
    }
  },
  "totals": {
    "onshore_mw": 158.629996,
    "offshore_mw": 171.729994,
    "total_mw": 330.35999000000004
  },
  "latest_timestamp_utc": "2026-01-20T11:15:00"
}