{
  "generated_at": "2026-05-07T11:04:25.519553+00:00",
  "source": "https://api.energidataservice.dk/dataset/ElectricityProdex5MinRealtime",
  "areas": {
    "DK1": {
      "price_area": "DK1",
      "timestamp_utc": "2026-05-07T11:00:00",
      "onshore_mw": 79.389999,
      "offshore_mw": -0.08,
      "total_mw": 79.309999
    },
    "DK2": {
      "price_area": "DK2",
      "timestamp_utc": "2026-05-07T11:00:00",
      "onshore_mw": 13.97,
      "offshore_mw": 18.440001,
      "total_mw": 32.410001
    }
  },
  "totals": {
    "onshore_mw": 93.359999,
    "offshore_mw": 18.360001,
    "total_mw": 111.72
  },
  "latest_timestamp_utc": "2026-05-07T11:00:00"
}